CyberSource/__init__.py
CyberSource/api_client.py
CyberSource/apis/__init__.py
CyberSource/apis/asymmetric_key_management_api.py
CyberSource/apis/capture_api.py
CyberSource/apis/conversion_details_api.py
CyberSource/apis/credit_api.py
CyberSource/apis/customer_api.py
CyberSource/apis/customer_payment_instrument_api.py
CyberSource/apis/customer_shipping_address_api.py
CyberSource/apis/decision_manager_api.py
CyberSource/apis/download_dtd_api.py
CyberSource/apis/download_xsd_api.py
CyberSource/apis/instrument_identifier_api.py
CyberSource/apis/invoice_settings_api.py
CyberSource/apis/invoices_api.py
CyberSource/apis/key_generation_api.py
CyberSource/apis/net_fundings_api.py
CyberSource/apis/notification_of_changes_api.py
CyberSource/apis/payer_authentication_api.py
CyberSource/apis/payment_batch_summaries_api.py
CyberSource/apis/payment_instrument_api.py
CyberSource/apis/payments_api.py
CyberSource/apis/payouts_api.py
CyberSource/apis/purchase_and_refund_details_api.py
CyberSource/apis/refund_api.py
CyberSource/apis/report_definitions_api.py
CyberSource/apis/report_downloads_api.py
CyberSource/apis/report_subscriptions_api.py
CyberSource/apis/reports_api.py
CyberSource/apis/reversal_api.py
CyberSource/apis/search_transactions_api.py
CyberSource/apis/secure_file_share_api.py
CyberSource/apis/symmetric_key_management_api.py
CyberSource/apis/taxes_api.py
CyberSource/apis/transaction_batches_api.py
CyberSource/apis/transaction_details_api.py
CyberSource/apis/user_management_api.py
CyberSource/apis/user_management_search_api.py
CyberSource/apis/verification_api.py
CyberSource/apis/void_api.py
CyberSource/configuration.py
CyberSource/models/__init__.py
CyberSource/models/add_negative_list_request.py
CyberSource/models/auth_reversal_request.py
CyberSource/models/capture_payment_request.py
CyberSource/models/card_info.py
CyberSource/models/check_payer_auth_enrollment_request.py
CyberSource/models/create_adhoc_report_request.py
clean_cybersource_rest_client_python-0.0.22.dist-info/WHEEL
clean_cybersource_rest_client_python-0.0.22.dist-info/METADATA
clean_cybersource_rest_client_python-0.0.22.dist-info/RECORD
