Metadata-Version: 2.1
Name: clean-cybersource-rest-client-python
Version: 0.0.22
Summary: 
Author: Maximiliano Opitz
Author-email: maximiliano@cornershopapp.com
Requires-Python: >=3.7,<4.0
Classifier: Programming Language :: Python :: 3
Classifier: Programming Language :: Python :: 3.7
Classifier: Programming Language :: Python :: 3.8
Classifier: Programming Language :: Python :: 3.9
Requires-Dist: PyJWT (==1.6.4)
Requires-Dist: certifi (==2019.9.11)
Requires-Dist: pycryptodome (==3.9.8)
Requires-Dist: pyopenssl (==17.5.0)
Requires-Dist: python_dateutil (==2.5.3)
Requires-Dist: setuptools (==21.0.0)
Requires-Dist: six (>=1.12.0,<2.0.0)
Requires-Dist: urllib3 (>=1.25.3,<2.0.0)
